README.md
setup.py
fish_tool/__init__.py
fish_tool/config_base.py
fish_tool/log_tool.py
fish_tool/register.py
fish_tool/sys_tool.py
fish_tool.egg-info/PKG-INFO
fish_tool.egg-info/SOURCES.txt
fish_tool.egg-info/dependency_links.txt
fish_tool.egg-info/requires.txt
fish_tool.egg-info/top_level.txt
fish_tool/ai/__init__.py
fish_tool/ai/attentions.py
fish_tool/ai/echarts_tool.py
fish_tool/ai/group_list.py
fish_tool/ai/laboratory.py
fish_tool/ai/scorers.py
fish_tool/ai/torch_tool.py
fish_tool/ai/zh_trans.py
fish_tool/db/__init__.py
fish_tool/db/es_tool.py
fish_tool/db/mysql_tool.py
fish_tool/db/neo_tool.py
fish_tool/db/sqlite_tool.py
fish_tool/db/xmind_tool.py
fish_tool/db/zip_tool.py
fish_tool/net/__init__.py
fish_tool/net/api_tool.py
fish_tool/net/proxy_16yun.py
fish_tool/net/spider_tool.py