Metadata-Version: 2.1
Name: fish-tool
Version: 1.17
Summary: some tool code
Home-page: https://gitee.com/laowangzi/fish_tool
Author: aifish
Author-email: ofyu@163.com
Requires-Python: >=3.8
Provides-Extra: AI
Provides-Extra: db
